baba/__init__.py
baba/crypto.py
baba/db.py
baba/engine.py
baba/session.py
babadb-1.1.2.dist-info/METADATA
babadb-1.1.2.dist-info/WHEEL
babadb-1.1.2.dist-info/top_level.txt
babadb-1.1.2.dist-info/RECORD
