Metadata-Version: 2.4
Name: babadb
Version: 1.1.2
Summary: Encrypted Async File-Based Database for Pydantic Models
Author-email: noxzion <negroid2281488ilikrilex@gmail.com>
License: MIT
Keywords: database,async,pydantic,encryption,file-based
Requires-Python: >=3.8
Requires-Dist: pydantic>=1.10.22
